smartstats/__init__.py
smartstats-0.4.dist-info/DESCRIPTION.rst
smartstats-0.4.dist-info/METADATA
smartstats-0.4.dist-info/RECORD
smartstats-0.4.dist-info/WHEEL
smartstats-0.4.dist-info/metadata.json
smartstats-0.4.dist-info/top_level.txt
