Metadata-Version: 2.0
Name: smartstats
Version: 0.4
Summary: Pretty Statistics
Home-page: http://github.com/andrewbschneider/smartstats
Author: Andrew Schneider
Author-email: andrewbschneider@gmail.com
License: MIT
Platform: UNKNOWN
Requires-Dist: numpy
Requires-Dist: pandas
Requires-Dist: scipy
Requires-Dist: statsmodels
Requires-Dist: tableprint
